{
"type": "FeatureCollection",
"name": "treetops",
"crs": { "type": "name", "properties": { "name": "urn:ogc:def:crs:OGC:1.3:CRS84" } },
"features": [
{ "type": "Feature", "properties": { "treeID": 18, "XTOP": 47195.34, "YTOP": 23916.94, "ZTOP": 42.57 }, "geometry": { "type": "Point", "coordinates": [ -122.459130240981281, 37.749251307662419 ] } },
{ "type": "Feature", "properties": { "treeID": 19, "XTOP": 47195.77, "YTOP": 23919.53, "ZTOP": 42.65 }, "geometry": { "type": "Point", "coordinates": [ -122.459125364762926, 37.749274642947 ] } },
{ "type": "Feature", "properties": { "treeID": 21, "XTOP": 47202.74, "YTOP": 23905.99, "ZTOP": 43.39 }, "geometry": { "type": "Point", "coordinates": [ -122.459046263343353, 37.749152658835044 ] } },
{ "type": "Feature", "properties": { "treeID": 23, "XTOP": 47208.52, "YTOP": 23911.38, "ZTOP": 42.77 }, "geometry": { "type": "Point", "coordinates": [ -122.458980685335362, 37.749201225684054 ] } }
]
}
